{
    "model": {
        "type": "minecraft:select",
        "property": "minecraft:component",
        "component": "minecraft:custom_name",
        "cases": [
            {
    "model": {
        "type": "minecraft:model",
        "model": "minecraft:item/wheacactinide"
        
    },
    "when": {"extra": [{"italic": false, "underlined": false, "bold": false, "color": "white", "obfuscated": false, "strikethrough": false, "text": "Wheacactinide"}], "text": ""}
}
        ],
        "fallback": {
            "type":"minecraft:model","model":"minecraft:item/cyan_dye"
        }
    }
}