{
    "model": {
        "type": "minecraft:select",
        "property": "minecraft:component",
        "component": "minecraft:custom_name",
        "cases": [
            {
    "model": {
        "type": "minecraft:model",
        "model": "minecraft:item/gift_of_giving"
        
    },
    "when": {"extra": [{"italic": false, "underlined": false, "bold": true, "color": "#F50059", "obfuscated": false, "strikethrough": false, "text": "Gift of Giving"}], "text": ""}
},{
    "model": {
        "type": "minecraft:model",
        "model": "minecraft:item/large_holiday_bonus"
        
    },
    "when": {"extra": [{"italic": false, "underlined": false, "bold": true, "color": "gold", "obfuscated": false, "strikethrough": false, "text": "Large Holiday Bonus"}], "text": ""}
},{
    "model": {
        "type": "minecraft:model",
        "model": "minecraft:item/getoutcredit"
        
    },
    "when": {"extra": [{"italic": false, "underlined": false, "bold": true, "color": "dark_purple", "obfuscated": false, "strikethrough": false, "text": "Get out of Jail Free Credit "},{"italic": false,"color": "gray", "text": "(Right Click)"}], "text": ""}
},{
    "model": {
        "type": "minecraft:model",
        "model": "minecraft:item/tagcredit"
        
    },
    "when": {"extra": [{"italic": false, "underlined": false, "bold": true, "color": "gold", "obfuscated": false, "strikethrough": false, "text": "Tag Credit"}], "text": ""}
}
        ],
        "fallback": {
            "type":"minecraft:model","model":"minecraft:item/emerald"
        }
    }
}